clicktypes/__init__.py
clicktypes/__version__.py
clicktypes/network/__init__.py
clicktypes/network/address.py
clicktypes/network/network.py
clicktypes/web/__init__.py
clicktypes/web/domain.py
clicktypes/web/email.py
clicktypes/web/url.py
clicktypes-0.0.7.dist-info/LICENSE
clicktypes-0.0.7.dist-info/METADATA
clicktypes-0.0.7.dist-info/WHEEL
clicktypes-0.0.7.dist-info/top_level.txt
clicktypes-0.0.7.dist-info/RECORD
